Metadata-Version: 2.1
Name: pyvcon
Version: 1.0.0
Summary: Python wrapper for Vcontacts
Home-page: https://github.com/gregorpatof/pyvcon_package
Author: Olivier Mailhot
License: UNKNOWN
Platform: UNKNOWN
Classifier: Programming Language :: Python :: 3
Classifier: License :: OSI Approved :: MIT License
Classifier: Operating System :: OS Independent
Requires-Python: >=3.6
